fillet/__init__.py
zen_fillet-1.0.0.dist-info/METADATA
zen_fillet-1.0.0.dist-info/WHEEL
zen_fillet-1.0.0.dist-info/top_level.txt
zen_fillet-1.0.0.dist-info/RECORD
