Metadata-Version: 2.1
Name: zen-fillet
Version: 1.0.0
Summary: Util to calculate fillet or chamfer radius by reducing or reducing by radius
Home-page: https://gitlab.com/hnau_zen/fillet
Author: Mark Zorikhin
Author-email: hnau256@gmail.com
License: UNKNOWN
Platform: UNKNOWN
Classifier: Programming Language :: Python :: 3
Classifier: License :: OSI Approved :: MIT License
Classifier: Operating System :: OS Independent
Requires-Python: >=3.6
